[
  {
    "uuid": "df0affd3-03cf-4966-9d80-d7a65ce5404f",
    "name": "Bigmanthan",
    "level": 1,
    "bypassesPlayerLimit": false
  },
  {
    "uuid": "6982c2e7-ead1-4d1b-b10e-859d8db8a644",
    "name": "ogawoga",
    "level": 1,
    "bypassesPlayerLimit": false
  },
  {
    "uuid": "a2d22eae-f838-4224-96e2-b2cc734510c6",
    "name": "dimondmania",
    "level": 1,
    "bypassesPlayerLimit": false
  },
  {
    "uuid": "e8d8f25b-757a-4f50-8d27-ca78d25a0bd9",
    "name": "xKqrmaV",
    "level": 1,
    "bypassesPlayerLimit": false
  },
  {
    "uuid": "1ca54b78-0dd5-49d1-8d5a-9ae546c63bcf",
    "name": "TheSoxFox",
    "level": 4,
    "bypassesPlayerLimit": false
  }
]